src/__init__.py
src/composition.py
src/config.py
src/exceptions.py
src/main.py
src/py.typed
src/tool_registry.py
src/tools.py
src/adapters/agent/capability_selector.py
src/adapters/agent/llm_executor.py
src/adapters/cli/__init__.py
src/adapters/cli/result_formatter.py
src/adapters/llm/grok_adapter.py
src/adapters/llm/mock_provider.py
src/entities/__init__.py
src/entities/agent.py
src/entities/execution.py
src/factories/__init__.py
src/factories/agent_factory.py
src/factories/provider_factory.py
src/interfaces/__init__.py
src/interfaces/agent_executor.py
src/interfaces/factory_interfaces.py
src/interfaces/llm_provider.py
src/interfaces/task_planner.py
src/use_cases/task_coordinator.py
src/use_cases/task_planner.py
unified_intelligence_cli-1.0.0.dist-info/licenses/LICENSE
unified_intelligence_cli-1.0.0.dist-info/METADATA
unified_intelligence_cli-1.0.0.dist-info/WHEEL
unified_intelligence_cli-1.0.0.dist-info/entry_points.txt
unified_intelligence_cli-1.0.0.dist-info/top_level.txt
unified_intelligence_cli-1.0.0.dist-info/RECORD
