Metadata-Version: 2.4
Name: unified-intelligence-cli
Version: 1.0.0
Summary: Production-ready multi-agent task orchestration framework with Clean Architecture
Author-email: Unified Intelligence CLI Team <noreply@example.com>
Maintainer-email: Unified Intelligence CLI Team <noreply@example.com>
License: MIT
Project-URL: Homepage, https://github.com/username/unified-intelligence-cli
Project-URL: Documentation, https://github.com/username/unified-intelligence-cli#readme
Project-URL: Repository, https://github.com/username/unified-intelligence-cli
Project-URL: Issues, https://github.com/username/unified-intelligence-cli/issues
Project-URL: Changelog, https://github.com/username/unified-intelligence-cli/releases
Keywords: ai,agents,multi-agent,orchestration,cli,llm,grok,automation,clean-architecture
Classifier: Development Status :: 5 - Production/Stable
Classifier: Intended Audience :: Developers
Classifier: License :: OSI Approved :: MIT License
Classifier: Operating System :: OS Independent
Classifier: Programming Language :: Python :: 3
Classifier: Programming Language :: Python :: 3.10
Classifier: Programming Language :: Python :: 3.11
Classifier: Programming Language :: Python :: 3.12
Classifier: Topic :: Software Development :: Libraries :: Python Modules
Classifier: Topic :: Scientific/Engineering :: Artificial Intelligence
Classifier: Typing :: Typed
Requires-Python: >=3.10
License-File: LICENSE
Requires-Dist: click>=8.0.0
Requires-Dist: httpx>=0.27.0
Requires-Dist: python-dotenv>=1.0.0
Provides-Extra: dev
Requires-Dist: pytest>=8.0.0; extra == "dev"
Requires-Dist: pytest-cov>=4.0.0; extra == "dev"
Requires-Dist: pytest-asyncio>=0.23.0; extra == "dev"
Requires-Dist: flake8>=7.0.0; extra == "dev"
Requires-Dist: black>=24.0.0; extra == "dev"
Requires-Dist: isort>=5.13.0; extra == "dev"
Requires-Dist: bandit>=1.7.0; extra == "dev"
Requires-Dist: safety>=3.0.0; extra == "dev"
Requires-Dist: mypy>=1.8.0; extra == "dev"
Dynamic: license-file
